Workbook

Sheet Instructions
A1: Projects for MBA Students (30 marks each)
A3: Purpose | B3: Each task asks students to build a working tool, bot, app, automation or analysis using only free LLM tools, then verify it and turn the result into a business recommendation.
A4: Allocation | B4: One task per student (or pair, if allowed). Allot by roll number or lottery so no two students in a section share a task.
A5: Files | B5: Every task has its own Excel file in the 'Task Files' folder: Task Brief (with rubric), ready-to-use dataset sheet(s), Data Dictionary and an AI Use Log template.
A6: Data | B6: All datasets are synthetic, generated for teaching, and free of real personal data. Companies, people and prices are fictional. Some files contain a 'Gold Labels (evaluation)' sheet that students must not give to the AI - it is for measuring accuracy.
A7: Free tools | B7: ChatGPT, Gemini (incl. Canvas and Gems), Claude, Microsoft Copilot, NotebookLM, Google AI Studio, Google Colab, Google Sheets + Apps Script, Canva, and free tiers of Make / Zapier / n8n. Free-tier limits change; students should note the plan they used.
A8: Expected effort | B8: 10-15 hours over 2-3 weeks.
A9: Evaluation | B9: Use the 'Rubric (30 marks)' sheet. Check at least 3 entries in each AI Use Log, ask each student to demo the build live for 3-5 minutes, and spot-check 3 numbers or labels in their output.
A10: Penalties (suggested) | B10: No AI Use Log: total capped at 15. Build does not run and no recording: criterion 1 capped at 2. Gold labels given to the AI: criterion 2 = 0. Copied work: referral under academic integrity policy.

Sheet Tasks
A1: Number | B1: Name | C1: Task ID | D1: Theme | E1: Task | F1: What students do | G1: Deliverables | H1: Datasets needed | I1: Excel file | J1: Suggested free tools | K1: GitHubLink
A2: 26030242002 | B2: Acharya Samyak Laxmikantbhai | C2: T01 | D2: A. No-code apps & dashboards | E2: Sales performance dashboard app | F2: 1. Upload the sales file to an LLM and ask it to build an interactive web dashboard (filters for month, region, channel, category). 2. Show KPIs: revenue, units, average order value, gross margin %, top 10 products, month-on-month growth. 3. Iterate at least 5 times on the prompt to fix layout and logic errors. 4. Re-compute every KPI in an Excel pivot and reconcile differences with the dashboard. 5. Write 5 insights a regional sales head could act on. | G2: Working dashboard (link or HTML file); KPI reconciliation sheet; 1-page insight note; AI-use log | H2: Synthetic D2C sales transactions, FY2025-26 (2,000 orders) — sheets: Sales (2,000 rows) | I2: T01_Sales_performance_dashboard_app.xlsx | J2: Gemini Canvas, ChatGPT Canvas or Claude (free) to generate the app; Excel / Google Sheets to verify numbers
A3: 26030242003 | B3: Aditya Atul Jewalikar | C3: T02 | D3: A. No-code apps & dashboards | E3: Marketing ROI calculator | F3: 1. Ask an LLM to build an app that calculates CTR, conversion rate, CPC, CAC and ROAS for each campaign. 2. Add a what-if slider that moves budget between channels and shows projected revenue. 3. Check 10 campaigns by hand in Excel. 4. Recommend how to re-split next quarter's budget. | G3: ROI calculator app; verification sheet; budget reallocation memo; AI-use log | H3: 60 digital campaigns with spend, impressions, clicks, conversions — sheets: Campaigns (60 rows) | I3: T02_Marketing_ROI_calculator.xlsx | J3: Gemini Canvas, ChatGPT Canvas or Claude (free) to generate the app; Excel / Google Sheets to verify numbers
A4: 26030242004 | B4: Akshita Mundra | C4: T03 | D4: A. No-code apps & dashboards | E4: Inventory reorder alert tool | F4: 1. Build an app that computes safety stock, reorder point and EOQ for each SKU (let the LLM explain each formula first). 2. Flag SKUs below reorder point and estimate days of stock left. 3. Verify 10 SKUs manually. 4. Draft a purchase list for the warehouse manager. | G4: Reorder app; formula explanation; purchase list; AI-use log | H4: 150 SKUs with stock, demand, lead time, costs — sheets: Inventory (150 rows) | I4: T03_Inventory_reorder_alert_tool.xlsx | J4: Gemini Canvas, ChatGPT Canvas or Claude (free) to generate the app; Excel / Google Sheets to verify numbers
A5: 26030242005 | B5: Anamika Gupta | C5: T04 | D5: A. No-code apps & dashboards | E5: Loan EMI and eligibility calculator | F5: 1. Build a calculator for EMI and FOIR (EMIs as % of income) with an eligibility rule (FOIR <= 50%, credit score >= 700). 2. Run all 500 applications through your rule and compare with the actual default flag. 3. Tune the rule to reduce defaults without rejecting too many good applicants. 4. Explain the trade-off to a credit manager. | G5: Calculator app; rule-testing sheet; 1-page credit policy note; AI-use log | H5: 500 loan applications with income, EMIs, credit score and 24-month default outcome — sheets: Applications (500 rows) | I5: T04_Loan_EMI_and_eligibility_calculator.xlsx | J5: Gemini Canvas, ChatGPT Canvas or Claude (free) to generate the app; Excel / Google Sheets to verify numbers
A6: 26030242008 | B6: Anjali Saxena | C6: T05 | D6: A. No-code apps & dashboards | E6: HR attrition insights dashboard | F6: 1. Build a dashboard of attrition by department, level, tenure, overtime and engagement. 2. Ask the LLM for hypotheses, then test each with a pivot table. 3. Identify the 3 strongest drivers. 4. Propose retention actions with rough cost. | G6: Dashboard; hypothesis-test table; retention plan; AI-use log | H6: 800 employees with engagement, overtime, promotion history and exit flag — sheets: Employees (800 rows) | I6: T05_HR_attrition_insights_dashboard.xlsx | J6: Gemini Canvas, ChatGPT Canvas or Claude (free) to generate the app; Excel / Google Sheets to verify numbers
A7: 26030242009 | B7: Arpit Gupta | C7: T06 | D7: A. No-code apps & dashboards | E7: Expense claim policy checker | F7: 1. Convert the travel policy rules into checks with the help of an LLM. 2. Build a tool that flags each claim as compliant or violation, with the rule broken. 3. Manually audit 30 flagged claims to measure false alarms. 4. Summarise the top violation types for the CFO. | G7: Checker tool; audit sheet; CFO summary; AI-use log | H7: 400 expense claims + 15 travel policy rules — sheets: Claims (400 rows); Policy Rules (15 rows) | I7: T06_Expense_claim_policy_checker.xlsx | J7: Gemini Canvas, ChatGPT Canvas or Claude (free) to generate the app; Excel / Google Sheets to verify numbers
A8: 26030242010 | B8: Arya | C8: T07 | D8: A. No-code apps & dashboards | E8: Pricing simulator | F8: 1. Use an LLM to estimate price elasticity for each product from the weekly data (log-log regression explained in plain language). 2. Build a simulator: change price and see predicted units and revenue. 3. Find the revenue-maximising price for each product. 4. Discuss competitor and promotion effects. | G8: Simulator app; elasticity estimates; pricing recommendation; AI-use log | H8: 3 products x 104 weeks of price, competitor price, promotions, units — sheets: Weekly Price-Demand (312 rows) | I8: T07_Pricing_simulator.xlsx | J8: Gemini Canvas, ChatGPT Canvas or Claude (free) to generate the app; Excel / Google Sheets to verify numbers
A9: 26030242011 | B9: Atal Ayush Ganesh | C9: T08 | D9: A. No-code apps & dashboards | E9: Startup unit-economics calculator | F9: 1. Build an app computing contribution margin, break-even units, CAC payback, LTV and months of runway. 2. Run it for all 10 startups. 3. Rank which ones an angel investor should meet. 4. Stress-test with 20% lower growth. | G9: Calculator app; ranking table; investor memo; AI-use log | H9: 10 fictional startups with price, costs, growth, CAC, churn, funding ask — sheets: Startups (10 rows) | I9: T08_Startup_unit_economics_calculator.xlsx | J9: Gemini Canvas, ChatGPT Canvas or Claude (free) to generate the app; Excel / Google Sheets to verify numbers
A10: 26030242012 | B10: Bandari Vedasvi | C10: T09 | D10: A. No-code apps & dashboards | E10: Customer RFM segmentation tool | F10: 1. Ask an LLM to write code that computes recency, frequency and monetary scores per customer. 2. Create segments (Champions, Loyal, At Risk, Lost, etc.). 3. Build a simple app to look up any customer's segment. 4. Design one campaign per segment. | G10: Notebook + app; segment table; campaign plan; AI-use log | H10: 3,000 orders linked to 450 customers — sheets: Sales (3,000 rows) | I10: T09_Customer_RFM_segmentation_tool.xlsx | J10: Google Colab with its built-in Gemini assistant, or any free chatbot, to write Python; publish on Streamlit Community Cloud or Hugging Face Spaces (free)
A11: 26030242013 | B11: Bibaswan Kundu | C11: T10 | D11: A. No-code apps & dashboards | E11: Regional sales forecaster | F11: 1. Use an LLM to write forecasting code (moving average, exponential smoothing, simple regression). 2. Forecast the next 6 months by region. 3. Back-test on the last 6 known months and report MAPE. 4. Present a forecast chart for the sales review. | G11: Forecast notebook/app; accuracy table; forecast chart; AI-use log | H11: 36 months of net sales by 4 regions — sheets: Monthly Sales (144 rows) | I11: T10_Regional_sales_forecaster.xlsx | J11: Google Colab with its built-in Gemini assistant, or any free chatbot, to write Python; publish on Streamlit Community Cloud or Hugging Face Spaces (free)
A12: 26030242014 | B12: Chinta Karthikeya Santosh Reddy | C12: T11 | D12: A. No-code apps & dashboards | E12: Hotel revenue dashboard | F12: 1. Build a dashboard of occupancy, ADR, RevPAR, cancellation rate and net revenue after OTA commission. 2. Compare channels on net revenue per booking. 3. Ask the LLM to propose an overbooking and channel strategy; test it on the data. 4. Recommend actions for the next season. | G12: Dashboard; channel profitability table; strategy note; AI-use log | H12: 1,500 bookings for a 120-room fictional hotel — sheets: Bookings (1,500 rows); Hotel Info (3 rows) | I12: T11_Hotel_revenue_dashboard.xlsx | J12: Gemini Canvas, ChatGPT Canvas or Claude (free) to generate the app; Excel / Google Sheets to verify numbers
A13: 26030242016 | B13: Dheemhan Saravanan | C13: T12 | D13: A. No-code apps & dashboards | E13: Delivery performance tracker | F13: 1. Build a tracker of on-time %, average delay, cost per kg and damage/RTO rate by carrier and region. 2. Rank carriers on a weighted scorecard. 3. Estimate savings from shifting volume to the best carriers. 4. Draft a carrier review email. | G13: Tracker app; carrier scorecard; savings estimate; AI-use log | H13: 1,200 shipments with carrier, distance, dates, freight cost, status — sheets: Shipments (1,200 rows) | I13: T12_Delivery_performance_tracker.xlsx | J13: Gemini Canvas, ChatGPT Canvas or Claude (free) to generate the app; Excel / Google Sheets to verify numbers
... A54: 26030242073 | B54: Taruna Raju Raskar | C54: T53 | D54: D. Marketing & content builds | E54: Email A/B test analyser | F54: 1. Build a tool that computes open and click rates with significance (let an LLM explain the test). 2. Analyse all 20 tests. 3. Identify winning patterns. 4. Generate 5 new test ideas. | G54: A/B tool; results table; test ideas; AI-use log | H54: 20 email A/B test results — sheets: AB Tests (20 rows) | I54: T53_Email_A_B_test_analyser.xlsx | J54: Gemini Canvas, ChatGPT Canvas or Claude (free) to generate the app; Excel / Google Sheets to verify numbers

Sheet Theme Summary
A1: Theme | B1: Number of tasks
A2: A. No-code apps & dashboards | B2: =COUNTIF(Tasks!$D$2:$D$81,A2) -> 20
A3: B. Chatbots & AI assistants | B3: =COUNTIF(Tasks!$D$2:$D$81,A3) -> 15
A4: C. AI text analytics | B4: =COUNTIF(Tasks!$D$2:$D$81,A4) -> 15
A5: D. Marketing & content builds | B5: =COUNTIF(Tasks!$D$2:$D$81,A5) -> 3
A6: E. Finance & operations automation | B6: =COUNTIF(Tasks!$D$2:$D$81,A6) -> 0
A7: F. Analytics tools built with AI-written code | B7: =COUNTIF(Tasks!$D$2:$D$81,A7) -> 0
A8: Total | B8: =SUM(B2:B7) -> 53

Sheet Rubric (30 marks)
A1: Criterion | B1: Marks | C1: What is assessed | D1: Excellent | E1: Good | F1: Fair | G1: Poor
A2: 1. Working build | B2: 8 | C2: Tool / bot / app / automation works end to end on the provided data; link, file or screen recording submitted | D2: Runs fully (7-8) | E2: Minor gaps (5-6) | F2: Partly working (3-4) | G2: Not working (0-2)
A3: 2. Correctness and verification | B3: 7 | C3: Outputs checked against the data or gold labels; accuracy measured; errors found and fixed | D3: Systematic checks with numbers (6-7) | E3: Some checks (4-5) | F3: Few checks (2-3) | G3: None (0-1)
A4: 3. Prompting and iteration | B4: 5 | C4: Clear, structured prompts; at least 3 documented improvement rounds with reasons | D4: Strong iteration (5) | E4: Some iteration (3-4) | F4: Mostly one-shot (2) | G4: No log (0-1)
A5: 4. Business insight and recommendation | B5: 6 | C5: Specific, data-backed recommendation for the stated manager or customer | D5: Actionable and quantified (6) | E5: Sound but generic (4-5) | F5: Descriptive only (2-3) | G5: Missing (0-1)
A6: 5. Documentation and reflection | B6: 4 | C6: Complete AI-use log, limitations, responsible-AI notes and personal reflection | D6: Complete and honest (4) | E6: Mostly complete (3) | F6: Thin (2) | G6: Missing (0-1)
A7: Total | B7: =SUM(B2:B6) -> 30

Sheet Marks Sheet
A1: Marks entry - yellow cells are for the evaluator; total and grade calculate automatically.
A2: Roll no | B2: Student name | C2: Task ID | D2: 1. Working build (8) | E2: 2. Correctness (7) | F2: 3. Prompting (5) | G2: 4. Insight (6) | H2: 5. Documentation (4) | I2: Penalty (enter as negative) | J2: Total (30) | K2: Grade | L2: Feedback
A3: MBA001 | B3: Example Student | C3: T07 | D3: 7 | E3: 6 | F3: 4 | G3: 5 | H3: 3 | I3: 0 | J3: =IF(COUNT(D3:H3)=0,"",MAX(0,SUM(D3:H3)+N(I3))) -> 25 | K3: =IF(J3="","",IF(J3>=27,"Outstanding",IF(J3>=22,"Very good",IF(J3>=17,"Good",IF(J3>=12,"Satisfactory","Needs rework"))))) -> Very good
J4: =IF(COUNT(D4:H4)=0,"",MAX(0,SUM(D4:H4)+N(I4))) | K4: =IF(J4="","",IF(J4>=27,"Outstanding",IF(J4>=22,"Very good",IF(J4>=17,"Good",IF(J4>=12,"Satisfactory","Needs rework")))))
J5: =IF(COUNT(D5:H5)=0,"",MAX(0,SUM(D5:H5)+N(I5))) | K5: =IF(J5="","",IF(J5>=27,"Outstanding",IF(J5>=22,"Very good",IF(J5>=17,"Good",IF(J5>=12,"Satisfactory","Needs rework")))))
J6: =IF(COUNT(D6:H6)=0,"",MAX(0,SUM(D6:H6)+N(I6))) | K6: =IF(J6="","",IF(J6>=27,"Outstanding",IF(J6>=22,"Very good",IF(J6>=17,"Good",IF(J6>=12,"Satisfactory","Needs rework")))))
J7: =IF(COUNT(D7:H7)=0,"",MAX(0,SUM(D7:H7)+N(I7))) | K7: =IF(J7="","",IF(J7>=27,"Outstanding",IF(J7>=22,"Very good",IF(J7>=17,"Good",IF(J7>=12,"Satisfactory","Needs rework")))))
J8: =IF(COUNT(D8:H8)=0,"",MAX(0,SUM(D8:H8)+N(I8))) | K8: =IF(J8="","",IF(J8>=27,"Outstanding",IF(J8>=22,"Very good",IF(J8>=17,"Good",IF(J8>=12,"Satisfactory","Needs rework")))))
J9: =IF(COUNT(D9:H9)=0,"",MAX(0,SUM(D9:H9)+N(I9))) | K9: =IF(J9="","",IF(J9>=27,"Outstanding",IF(J9>=22,"Very good",IF(J9>=17,"Good",IF(J9>=12,"Satisfactory","Needs rework")))))
J10: =IF(COUNT(D10:H10)=0,"",MAX(0,SUM(D10:H10)+N(I10))) | K10: =IF(J10="","",IF(J10>=27,"Outstanding",IF(J10>=22,"Very good",IF(J10>=17,"Good",IF(J10>=12,"Satisfactory","Needs rework")))))
J11: =IF(COUNT(D11:H11)=0,"",MAX(0,SUM(D11:H11)+N(I11))) | K11: =IF(J11="","",IF(J11>=27,"Outstanding",IF(J11>=22,"Very good",IF(J11>=17,"Good",IF(J11>=12,"Satisfactory","Needs rework")))))
J12: =IF(COUNT(D12:H12)=0,"",MAX(0,SUM(D12:H12)+N(I12))) | K12: =IF(J12="","",IF(J12>=27,"Outstanding",IF(J12>=22,"Very good",IF(J12>=17,"Good",IF(J12>=12,"Satisfactory","Needs rework")))))
J13: =IF(COUNT(D13:H13)=0,"",MAX(0,SUM(D13:H13)+N(I13))) | K13: =IF(J13="","",IF(J13>=27,"Outstanding",IF(J13>=22,"Very good",IF(J13>=17,"Good",IF(J13>=12,"Satisfactory","Needs rework")))))
J14: =IF(COUNT(D14:H14)=0,"",MAX(0,SUM(D14:H14)+N(I14))) | K14: =IF(J14="","",IF(J14>=27,"Outstanding",IF(J14>=22,"Very good",IF(J14>=17,"Good",IF(J14>=12,"Satisfactory","Needs rework")))))
J15: =IF(COUNT(D15:H15)=0,"",MAX(0,SUM(D15:H15)+N(I15))) | K15: =IF(J15="","",IF(J15>=27,"Outstanding",IF(J15>=22,"Very good",IF(J15>=17,"Good",IF(J15>=12,"Satisfactory","Needs rework")))))
... J82: =IF(COUNT(D82:H82)=0,"",MAX(0,SUM(D82:H82)+N(I82))) | K82: =IF(J82="","",IF(J82>=27,"Outstanding",IF(J82>=22,"Very good",IF(J82>=17,"Good",IF(J82>=12,"Satisfactory","Needs rework")))))
